ddoc/__init__.py
ddoc/builtin_plugins/__init__.py
ddoc/builtin_plugins/builtin_impls.py
ddoc/cli/__init__.py
ddoc/cli/commands.py
ddoc/cli/main.py
ddoc/cli/plugins.py
ddoc/config/config.json
ddoc/core/__init__.py
ddoc/core/config.py
ddoc/core/io.py
ddoc/core/logging.py
ddoc/core/pipeline.py
ddoc/core/plugins.py
ddoc/fonts/NanumGothicCoding-Bold.ttf
ddoc/fonts/NanumGothicCoding-Regular.ttf
ddoc/ops/__init__.py
ddoc/ops/core_ops.py
ddoc/plugins/__init__.py
ddoc/plugins/hookspecs.py
ddoc/utils/__init__.py
ddoc/utils/io.py
ddoc-0.1.3.3.dist-info/licenses/LICENSE
ddoc-0.1.3.3.dist-info/METADATA
ddoc-0.1.3.3.dist-info/WHEEL
ddoc-0.1.3.3.dist-info/entry_points.txt
ddoc-0.1.3.3.dist-info/top_level.txt
ddoc-0.1.3.3.dist-info/RECORD
