Metadata-Version: 2.4
Name: ddoc
Version: 0.1.3.3
Summary: ddoc: Data doctor for data drift
License: Apache2.0
License-File: LICENSE
Requires-Dist: fastapi
Requires-Dist: uvicorn
Requires-Dist: requests
Requires-Dist: pandas
Requires-Dist: numpy
Requires-Dist: scikit-learn
Requires-Dist: pyyaml
Requires-Dist: fpdf
Requires-Dist: weasyprint
Requires-Dist: pluggy>=1.5.0
Requires-Dist: typer>=0.12
Requires-Dist: rich>=13.7
Requires-Dist: pydantic>=2.7
Requires-Dist: typer
Dynamic: license
Dynamic: license-file
Dynamic: requires-dist
Dynamic: summary
